easy_cherry/__init__.py
easy_cherry/db_logger_auto.py
easy_cherry/py.typed
easy_cherry/slack.py
easy_cherry/telegram.py
easy_cherry-1.6.6.dist-info/licenses/LICENSE
easy_cherry-1.6.6.dist-info/METADATA
easy_cherry-1.6.6.dist-info/WHEEL
easy_cherry-1.6.6.dist-info/top_level.txt
easy_cherry-1.6.6.dist-info/RECORD
