Metadata-Version: 2.4
Name: easy-cherry
Version: 1.6.6
Summary: Your library's description.
Author-email: Vinay <vinay.me223@gmail.com>
Classifier: Programming Language :: Python :: 3
Classifier: License :: OSI Approved :: MIT License
Classifier: Operating System :: OS Independent
Requires-Python: >=3.8
License-File: LICENSE
Requires-Dist: psycopg2-binary
Requires-Dist: python-dotenv
Requires-Dist: tenacity
Requires-Dist: slack_sdk
Requires-Dist: html2text
Dynamic: license-file
